gtvision/__init__.py
gtvision/datasets/__init__.py
gtvision/datasets/folder.py
gtvision/datasets/mnist.py
gtvision/transforms/__init__.py
gtvision/transforms/factory.py
gtvision-0.0.0a5.dist-info/LICENSE
gtvision-0.0.0a5.dist-info/METADATA
gtvision-0.0.0a5.dist-info/WHEEL
gtvision-0.0.0a5.dist-info/RECORD
